mollib/__init__.py
mollib/__main__.py
mollib/__version__.py
mollib/core/__init__.py
mollib/core/atom.py
mollib/core/chain.py
mollib/core/geometry.c
mollib/core/geometry.pyx
mollib/core/geometry.so
mollib/core/geometry_box.c
mollib/core/geometry_box.pxd
mollib/core/geometry_box.pyx
mollib/core/geometry_box.so
mollib/core/molecule.py
mollib/core/primitives.py
mollib/core/residue.py
mollib/core/settings.py
mollib/core/settings_manager.py
mollib/core/topology.py
mollib/core/utils.py
mollib/core/plugins/__init__.py
mollib/core/plugins/measure.py
mollib/core/plugins/process.py
mollib/core/readers/__init__.py
mollib/core/readers/base.py
mollib/core/readers/pdb.py
mollib/data/high_res.txt
mollib/data/high_res_short.txt
mollib/data/hbondstatistics/bb-bb amide__310-helix.npz
mollib/data/hbondstatistics/bb-bb amide__alpha-helix.npz
mollib/data/hbondstatistics/bb-bb amide__isolated.npz
mollib/data/hbondstatistics/bb-bb amide__pi-helix.npz
mollib/data/hbondstatistics/bb-bb amide__sheet.npz
mollib/data/hbondstatistics/bb-bb amide__type I turn.npz
mollib/data/hbondstatistics/bb-bb amide__type I' turn.npz
mollib/data/hbondstatistics/bb-bb amide__type II turn.npz
mollib/data/hbondstatistics/bb-bb amide__type II' turn.npz
mollib/data/hbondstatistics/bb-sc amide__isolated.npz
mollib/data/hbondstatistics/isolated.npz
mollib/data/hbondstatistics/sc-bb amide__isolated.npz
mollib/data/hbondstatistics/sc-bb hydroxyl__isolated.npz
mollib/data/hbondstatistics/sc-sc amide__isolated.npz
mollib/data/hbondstatistics/sc-sc hydroxyl__isolated.npz
mollib/data/ramachandranstatistics/310-helix.npz
mollib/data/ramachandranstatistics/alpha-helix.npz
mollib/data/ramachandranstatistics/alpha-helix__C-term.npz
mollib/data/ramachandranstatistics/alpha-helix__N-term.npz
mollib/data/ramachandranstatistics/Gly.npz
mollib/data/ramachandranstatistics/No classification.npz
mollib/data/ramachandranstatistics/pi-helix.npz
mollib-1.0.9.dist-info/DESCRIPTION.rst
mollib-1.0.9.dist-info/entry_points.txt
mollib-1.0.9.dist-info/METADATA
mollib-1.0.9.dist-info/metadata.json
mollib-1.0.9.dist-info/RECORD
mollib-1.0.9.dist-info/top_level.txt
mollib-1.0.9.dist-info/WHEEL
