Metadata-Version: 2.0
Name: mollib
Version: 1.0.9
Summary: UNKNOWN
Home-page: http://mollib.readthedocs.io/en/latest/
Author: Justin L Lorieau
Author-email: UNKNOWN
License: GPLv3
Download-URL: https://pypi.python.org/pypi/mollib/
Platform: any
Classifier: Development Status :: 5 - Production/Stable
Classifier: Intended Audience :: Science/Research
Classifier: License :: OSI Approved :: GNU General Public License v3 (GPLv3)
Classifier: Operating System :: MacOS :: MacOS X
Classifier: Operating System :: POSIX :: Linux
Classifier: Programming Language :: C
Classifier: Programming Language :: Python
Classifier: Programming Language :: Python :: 2.7
Classifier: Programming Language :: Python :: 3
Classifier: Programming Language :: Python :: 3.5
Classifier: Programming Language :: Python :: 3.6
Classifier: Topic :: Scientific/Engineering
Classifier: Topic :: Scientific/Engineering :: Chemistry
Requires-Dist: configparser
Requires-Dist: numpy
Requires-Dist: scipy
